iphoto_exporter.py
iphoto_exporter-0.0.3.dist-info/METADATA
iphoto_exporter-0.0.3.dist-info/RECORD
iphoto_exporter-0.0.3.dist-info/WHEEL
iphoto_exporter-0.0.3.dist-info/entry_points.txt
iphoto_exporter-0.0.3.dist-info/top_level.txt
