Metadata-Version: 2.1
Name: iphoto-exporter
Version: 0.0.3
Summary: Simple exporter for master images from iPhoto Libraries
Home-page: https://github.com/janwh/iphoto-exporter
Author: Jan Willhaus
Author-email: mail@janwillhaus.de
License: MIT
Keywords: iphoto photos.app exporter
Platform: UNKNOWN
Classifier: Development Status :: 4 - Beta
Classifier: Intended Audience :: Developers
Classifier: Intended Audience :: End Users/Desktop
Classifier: Intended Audience :: System Administrators
Classifier: Operating System :: MacOS :: MacOS X
Classifier: Topic :: System :: Recovery Tools
Classifier: License :: OSI Approved :: MIT License
Classifier: Programming Language :: Python :: 3
Classifier: Programming Language :: Python :: 3.4
Classifier: Programming Language :: Python :: 3.5
Classifier: Programming Language :: Python :: 3.6
Requires-Python: >=3
Requires-Dist: awesome-slugify
Requires-Dist: tqdm
